README.rst
setup.py
ADiPy.egg-info/PKG-INFO
ADiPy.egg-info/SOURCES.txt
ADiPy.egg-info/dependency_links.txt
ADiPy.egg-info/requires.txt
ADiPy.egg-info/top_level.txt
adipy/__init__.py
adipy/adipy.py
adipy/linalg/__init__.py
adipy/linalg/linalg.py