Metadata-Version: 1.1
Name: ADiPy
Version: 0.6.3
Summary: Automatic Differentiation for Python
Home-page: https://github.com/tisimst/adipy
Author: Abraham Lee
Author-email: tisimst@gmail.com
License: BSD License
Keywords: automatic differentiation,algorithmic differentiation,arbitrary order,python,linear algebra
Platform: UNKNOWN
Classifier: Development Status :: 5 - Production/Stable
Classifier: Intended Audience :: Education
Classifier: Intended Audience :: Science/Research
Classifier: License :: OSI Approved :: BSD License
Classifier: Operating System :: OS Independent
Classifier: Programming Language :: Python
Classifier: Programming Language :: Python :: 2.6
Classifier: Programming Language :: Python :: 2.7
Classifier: Topic :: Education
Classifier: Topic :: Scientific/Engineering
Classifier: Topic :: Scientific/Engineering :: Mathematics
Classifier: Topic :: Scientific/Engineering :: Physics
Classifier: Topic :: Software Development
Classifier: Topic :: Software Development :: Libraries
Classifier: Topic :: Software Development :: Libraries :: Python Modules
Classifier: Topic :: Utilities
